rtl/core/sddu.sv
//Metadata follows lane 0 / maximum-delay timing and is valid only when out_valid is high.
`timescale 1ns/1ps

import edgeasic_config_pkg::*;

module sddu (

    input logic clk,
    input logic rst_n,
    input logic in_valid,
    input logic enable,
    input logic signed [ARRAY_N*ACC_W-1:0] in_psum_bus,
    input logic in_k_tile_first,
    input logic in_k_tile_last,

    output logic out_valid,
    output logic signed [ARRAY_N*ACC_W-1:0] out_psum_bus,
    output logic out_k_tile_first,
    output logic out_k_tile_last

);

    localparam int MAX_DELAY=ARRAY_N-1;
    logic signed [ACC_W-1:0] psum_pipe [0:ARRAY_N-1][0:MAX_DELAY-1];
    logic valid_pipe [0:MAX_DELAY-1];
    logic k_tile_first_pipe [0:MAX_DELAY-1];
    logic k_tile_last_pipe [0:MAX_DELAY-1];

    always_ff @(posedge clk or negedge rst_n) begin
        if (!rst_n) begin
            for (int i = 0;i<ARRAY_N;i=i+1) begin
                for(int j=0;j<MAX_DELAY;j=j+1) begin
                    psum_pipe[i][j] <= '0;
                end
            end
            
            for (int i = 0;i<MAX_DELAY;i=i+1) begin
                valid_pipe[i] <= '0;
                k_tile_first_pipe[i] <= '0;
                k_tile_last_pipe[i] <= '0; 
            end
            
        end else if(enable) begin
        
        for (int i = 0;i<ARRAY_N;i=i+1) begin
            psum_pipe[i][0] <= $signed(in_psum_bus[i*ACC_W +:ACC_W]);
        for (int j=1; j<MAX_DELAY;j=j+1) begin
            psum_pipe[i][j] <= psum_pipe[i][j-1];
        end
        end
        valid_pipe[0] <= in_valid;
        k_tile_first_pipe[0] <= in_k_tile_first;
        k_tile_last_pipe[0] <= in_k_tile_last;
        for (int k=1;k<MAX_DELAY;k=k+1) begin
            valid_pipe[k] <= valid_pipe[k-1];
            k_tile_first_pipe[k] <= k_tile_first_pipe[k-1];
            k_tile_last_pipe[k] <= k_tile_last_pipe[k-1];
        end

    end
    end
    genvar c;
    generate
        for (c = 0; c< ARRAY_N;c=c+1) begin
            localparam int DELAY = MAX_DELAY-c;
            if (DELAY == 0) begin
                assign out_psum_bus[c*ACC_W +: ACC_W] = in_psum_bus[c*ACC_W +: ACC_W];
            end
            else begin
                assign out_psum_bus[c*ACC_W +: ACC_W] = psum_pipe[c][DELAY-1];
            end
            
        end
    endgenerate

    assign out_valid = valid_pipe[MAX_DELAY-1];
    assign out_k_tile_first = k_tile_first_pipe[MAX_DELAY-1];
    assign out_k_tile_last = k_tile_last_pipe[MAX_DELAY-1];


endmodule

tb/tb_SDDU.sv
`timescale 1ns/1ps

import edgeasic_config_pkg::*;

module tb_SDDU;

    logic clk;
    logic rst_n;
    logic in_valid;
    logic enable;
    logic signed [ARRAY_N*ACC_W-1:0] in_psum_bus;
    logic in_k_tile_first;
    logic in_k_tile_last;
    int mark;

    logic out_valid;
    logic signed [ARRAY_N*ACC_W-1:0] out_psum_bus;
    logic out_k_tile_first;
    logic out_k_tile_last;

    int errors;
    int errors4;
    int errors5;

    logic signed out_k_tile_first_held;
    logic signed out_k_tile_last_held;
    logic signed out_valid_held;
    logic signed [ARRAY_N*ACC_W-1:0] out_psum_bus_held;

    sddu dut(
        .clk(clk),
        .rst_n(rst_n),
        .in_valid(in_valid),
        .enable(enable),
        .in_psum_bus(in_psum_bus),
        .in_k_tile_first(in_k_tile_first),
        .in_k_tile_last(in_k_tile_last),
        .out_valid(out_valid),
        .out_psum_bus(out_psum_bus),
        .out_k_tile_first(out_k_tile_first),
        .out_k_tile_last(out_k_tile_last)
    );
    
    always #5 clk = ~clk;

    task reset_dut();
    begin 
        @(negedge clk);
        rst_n = 1'b0;
        enable = 1'b0;
        in_valid = 1'b0;
        in_psum_bus = '0;
        in_k_tile_first = 1'b0;
        in_k_tile_last = 1'b0;


        repeat(2) @(posedge clk);

        @(negedge clk);
        rst_n=1'b1;

        @(posedge clk);
        #1;

        $display("RESET COMPLETE");
    end    
    endtask

    task deskew_pipeline(input int lane_idx,input logic signed [ACC_W-1:0] marker_value);

    @(negedge clk);
    in_psum_bus = '0;
    in_psum_bus[lane_idx*ACC_W+:ACC_W] = marker_value;
    in_valid = 1'b1;
    enable = 1'b1;
    in_k_tile_first = (lane_idx == 0);
    in_k_tile_last = (lane_idx == 0);

    @(posedge clk);
    #1;


    endtask


    initial begin
        errors4 = 0;
        errors = 0;
        $dumpfile("sim/SDDU.vcd");
        $dumpvars(0,tb_SDDU);

        clk = 1'b0;
        rst_n = 1'b0;
        enable = 1'b0;
        in_valid = 1'b0;
        in_psum_bus = '0;
        in_k_tile_first = 1'b0;
        in_k_tile_last = 1'b0;

        #10;
        rst_n = 1'b1;
        #10;
        reset_dut();
        
        // ==========================================
        // TEST 1: CHECKING RESET
        // ==========================================
        $display("\n--- TEST 1: CHECKING RESET ---");
        @(negedge clk);
        in_valid = 1'b1;
        enable = 1'b1;
        in_psum_bus = 'd1;
        in_k_tile_first = 1'b1;
        in_k_tile_last = 1'b1;

        @(posedge clk);
        #1;

        reset_dut();
        @(negedge clk);
        #1;
        if (out_valid !== 1'b0) begin
            $error("RESET FAIL: out_valid = %b, expected 0", out_valid);
            errors++;
        end
        if (out_psum_bus !== '0) begin
            $error("RESET FAIL: out_psum_bus = %b, expected 0", out_psum_bus);
            errors++;
        end
        if (out_k_tile_first !== 1'b0) begin
            $error("RESET FAIL: out_k_tile_first = %b, expected 0", out_k_tile_first);
            errors++;
        end
        if (out_k_tile_last !== 1'b0) begin
            $error("RESET FAIL: out_k_tile_last = %b, expected 0", out_k_tile_last);
            errors++;
        end
        if (errors == 0)
            $display("RESET COMPLETE AND VERIFIED");
        else
            $display("RESET COMPLETE WITH %0d ERROR(S)", errors);
    
        
     // ==========================================
     // TEST 2: TESTING FOR DELAY
    // ==========================================
    $display("\n--- TEST 2: TESTING FOR DELAY ---"); 
    reset_dut();

    
    for(int i=0;i<ARRAY_N-1;i=i+1) begin

        mark =(i+1)*100;
        deskew_pipeline(i,mark);
    end

    @(negedge clk);

in_psum_bus = '0;
in_psum_bus[7*ACC_W +: ACC_W] = 800;

in_valid = 1'b1;
enable   = 1'b1;

#1;
    
    if(out_psum_bus[0*ACC_W +: ACC_W] !== 100)
        errors++;
    if(out_valid !== 1'b1 ) begin
        $display("out_valid = %b", out_valid);
        errors++; 
    end
    if(out_k_tile_first !== 1'b1 ) begin
        $display("out_k_tile_first = %b", out_k_tile_first);
        errors++;
    end
    if(out_k_tile_last !== 1'b1 ) begin
        $display("out_k_tile_last = %b", out_k_tile_last);
        errors++;
    end

    if(out_psum_bus[1*ACC_W +: ACC_W] !== 200)
        errors++;
    if(out_psum_bus[2*ACC_W +: ACC_W] !== 300)
        errors++;
   if(out_psum_bus[3*ACC_W +: ACC_W] !== 400)
        errors++;
   if(out_psum_bus[4*ACC_W +: ACC_W] !== 500)
        errors++;
   if(out_psum_bus[5*ACC_W +: ACC_W] !== 600)
        errors++;
   if(out_psum_bus[6*ACC_W +: ACC_W] !== 700)
        errors++;
   if(out_psum_bus[7*ACC_W +: ACC_W] !== 800)
        errors++;

    if(errors == 0)
        $display("TEST 2 PASSED");
    else
        $display("TEST 2 FAILED WITH %0d ERRORS", errors);


        

    // ==========================================
    // TEST 3: TESTING FOR OUT VALID
    // ==========================================
    $display("\n--- TEST 3: TESTING FOR OUT VALID ---"); 
    reset_dut();
    for(int i=0;i<ARRAY_N-1;i=i+1) begin

        mark =(i+1)*100;
        deskew_pipeline(i,mark);
        if(out_valid !== 1'b1) begin
            $display("OUT VALID IS ZERO");
        end
        else begin
            $display("OUT VALID IS ONE");
            errors++;
        end
    end

    @(negedge clk);

in_psum_bus = '0;
in_psum_bus[7*ACC_W +: ACC_W] = 800;

in_valid = 1'b1;
enable   = 1'b1;
in_k_tile_first=1'b0;
in_k_tile_last =1'b0;

if(out_valid === 1'b1) begin
    $display("OUT VALID IS One");
    end
    else begin
    $display("OUT VALID IS ZERO");
    errors++;
    end

if(errors==0)
    $display("TEST 3 PASSED");
else
    $display("TEST 3 FAILED WITH %0d ERRORS", errors);

// ==========================================
// TEST 4: CONTINUOUS 8x8 WAVEFRONT
// ==========================================
$display("\n--- TEST 4: CONTINUOUS 8x8 WAVEFRONT ---");

reset_dut();
errors4 = 0;

// Outer loop represents raw systolic-array output clocks.
// For ARRAY_N=8, it runs for 15 clocks.
for (int t = 0; t < (2*ARRAY_N-1); t = t + 1) begin

    @(negedge clk);

    // Clear every lane before constructing this clock's wavefront.
    in_psum_bus = '0;
    enable = 1'b1;

    // A new output row begins on lane 0 for clocks 0 through 7.
    in_valid = (t < ARRAY_N);

    // This test represents one K tile that is both first and last.
    in_k_tile_first = (t < ARRAY_N);
    in_k_tile_last  = (t < ARRAY_N);

    // Examine every output row.
    for (int row = 0; row < ARRAY_N; row = row + 1) begin

        // Examine every output lane/column.
        for (int lane = 0; lane < ARRAY_N; lane = lane + 1) begin

            // Result [row][lane] appears at raw clock row+lane.
            if (t == (row+lane)) begin
                in_psum_bus[lane*ACC_W +: ACC_W] =
                    100 + (10*row) + (lane+1);
            end

        end
    end

    // Lane 7 has zero SDDU delay, so let it settle.
    #1;

    // No complete output row should exist before clock 7.
    if (t < (ARRAY_N-1)) begin

        if (out_valid !== 1'b0) begin
            $error(
                "TEST 4: out_valid asserted early at raw clock %0d",
                t
            );
            errors4++;
        end

    end else begin

        // From t=7 through t=14, one complete row is expected.
        if (out_valid !== 1'b1) begin
            $error(
                "TEST 4: out_valid=0 at raw clock %0d",
                t
            );
            errors4++;
        end

        // Check all eight lanes of the aligned output row.
        for (int lane = 0; lane < ARRAY_N; lane = lane + 1) begin

            if ($signed(out_psum_bus[lane*ACC_W +: ACC_W])
                !==
                (100
                 + (10*(t-(ARRAY_N-1)))
                 + (lane+1))) begin

                $error(
                    "TEST 4: output row %0d lane %0d: actual=%0d expected=%0d",
                    t-(ARRAY_N-1),
                    lane,
                    $signed(out_psum_bus[lane*ACC_W +: ACC_W]),
                    100
                    + (10*(t-(ARRAY_N-1)))
                    + (lane+1)
                );
                errors4++;
            end

        end

        // FIRST/LAST must accompany every valid output row.
        if (out_k_tile_first !== 1'b1) begin
            $error(
                "TEST 4: FIRST incorrect for output row %0d",
                t-(ARRAY_N-1)
            );
            errors4++;
        end

        if (out_k_tile_last !== 1'b1) begin
            $error(
                "TEST 4: LAST incorrect for output row %0d",
                t-(ARRAY_N-1)
            );
            errors4++;
        end

    end
end

// Advance the SDDU once more after the final output row.
@(posedge clk);
#1;

if (out_valid !== 1'b0) begin
    $error("TEST 4: out_valid remained high after the final row");
    errors4++;
end

if (out_k_tile_first !== 1'b0) begin
    $error("TEST 4: FIRST remained high after the final row");
    errors4++;
end

if (out_k_tile_last !== 1'b0) begin
    $error("TEST 4: LAST remained high after the final row");
    errors4++;
end

if (errors4 == 0)
    $display("TEST 4 PASSED");
else
    $display("TEST 4 FAILED WITH %0d ERROR(S)", errors4);

// ==========================================
// TEST 5: enable check
// ==========================================
$display("\n--- TEST 5: ENABLE CHECK ---");

reset_dut();
errors5 = 0;

for (int t=0;t<ARRAY_N;t=t+1) begin
    @(negedge clk);
    
    in_psum_bus = '0;
    enable = 1'b1;

    in_valid = 1'b1;
    in_k_tile_first = 1'b1;
    in_k_tile_last = 1'b1;

    for (int row = 0; row < ARRAY_N; row = row + 1) begin
        for (int lane =0; lane < ARRAY_N; lane = lane+1) begin

            if (t== row + lane) begin
                in_psum_bus[lane*ACC_W+: ACC_W] = 1000 + 10*row + (lane+1);
            end
        end
    end

#1;
    if(t<(ARRAY_N-1))begin
        if (out_valid !== 1'b0) begin
            $error("TEST 5: out_valid asserted early at t=%0d",t);
            errors5++;
        end
    end
end
if (out_valid !== 1'b1) begin
    $error("TEST 5: No valid output row before stall");
    errors5++;
end
    out_psum_bus_held = out_psum_bus;
    out_k_tile_first_held = out_k_tile_first;
    out_k_tile_last_held = out_k_tile_last;
    out_valid_held = out_valid;

    enable = 1'b0;

    repeat(3) begin
    @(posedge clk);
    #1;

    if(out_psum_bus!==out_psum_bus_held)begin
        errors5++;
        $display("out_psum_bus_held = %h",out_psum_bus_held);
        $display("out_psum_bus = %h",out_psum_bus);
    end

    if(out_k_tile_first!==out_k_tile_first_held)begin
        errors5++;
        $display("out_k_tile_first_held = %b",out_k_tile_first_held);
        $display("out_k_tile_first = %b",out_k_tile_first);
    end

    if(out_k_tile_last!==out_k_tile_last_held)begin
        errors5++;
        $display("out_k_tile_last_held = %b",out_k_tile_last_held);
        $display("out_k_tile_last = %b",out_k_tile_last);
    end
    
    if(out_valid!==out_valid_held)begin
        errors5++;
        $display("out_valid_held = %b",out_valid_held);
        $display("out_valid = %b",out_valid);
    end
    end  

    @(negedge clk);
    enable=1'b1;

    @(posedge clk);
    #1;
    
for (int t=ARRAY_N;t<2*ARRAY_N-1;t=t+1) begin
    @(negedge clk);

    in_psum_bus = '0;
    in_valid = 1'b0;
    in_k_tile_first = 1'b0;
    in_k_tile_last = 1'b0;
    enable = 1'b1;

    for (int row = 0; row < ARRAY_N; row = row + 1) begin
        for (int lane =0; lane < ARRAY_N; lane = lane+1) begin

            if (t== row + lane) begin
                in_psum_bus[lane*ACC_W+: ACC_W] = 1000 + 10*row + (lane+1);
            end
        end
    end

#1;

    if (out_valid !== 1'b1) begin
    $error("TEST 5: No valid output row after resume");
    errors5++;
end   

    for (int lane = 0; lane < ARRAY_N; lane = lane + 1) begin
        if ($signed(out_psum_bus[lane*ACC_W +: ACC_W]) !== (1000 + 10*(t-(ARRAY_N-1)) + (lane+1))) begin

            $error("TEST 5: Resume row %0d lane %0d actual=%0d expected=%0d",
                t-(ARRAY_N-1),lane,$signed(out_psum_bus[lane*ACC_W +: ACC_W]),1000 + 10*(t-(ARRAY_N-1)) + (lane+1));
            errors5++;
        end
    end

    if (out_k_tile_first !== 1'b1) begin
        $error(
            "TEST 5: FIRST incorrect after resume on row %0d",
            t-(ARRAY_N-1)
        );
        errors5++;
    end

    if (out_k_tile_last !== 1'b1) begin
        $error(
            "TEST 5: LAST incorrect after resume on row %0d",
            t-(ARRAY_N-1)
        );
        errors5++;
    end
end

// Flush the final valid token.
@(posedge clk);
#1;

if (out_valid !== 1'b0) begin
    $error("TEST 5: out_valid remained high after final row");
    errors5++;
end

if (errors5 == 0)
    $display("TEST 5 PASSED");
else
    $display("TEST 5 FAILED WITH %0d ERROR(S)", errors5);



$finish;
end
endmodule

tb/sim/SDDU.vcd
$date
	Sat Jul 18 00:48:20 2026
$end
$version
	Icarus Verilog
$end
$timescale
	1ps
$end
$scope module tb_SDDU $end
$var wire 1 ! out_valid $end
$var wire 256 " out_psum_bus [255:0] $end
$var wire 1 # out_k_tile_last $end
$var wire 1 $ out_k_tile_first $end
$var reg 1 % clk $end
$var reg 1 & enable $end
$var reg 1 ' in_k_tile_first $end
$var reg 1 ( in_k_tile_last $end
$var reg 256 ) in_psum_bus [255:0] $end
$var reg 1 * in_valid $end
$var reg 1 + out_k_tile_first_held $end
$var reg 1 , out_k_tile_last_held $end
$var reg 256 - out_psum_bus_held [255:0] $end
$var reg 1 . out_valid_held $end
$var reg 1 / rst_n $end
$var integer 32 0 errors [31:0] $end
$var integer 32 1 errors4 [31:0] $end
$var integer 32 2 errors5 [31:0] $end
$var integer 32 3 mark [31:0] $end
$scope module dut $end
$var wire 1 % clk $end
$var wire 1 & enable $end
$var wire 1 ' in_k_tile_first $end
$var wire 1 ( in_k_tile_last $end
$var wire 256 4 in_psum_bus [255:0] $end
$var wire 1 * in_valid $end
$var wire 1 $ out_k_tile_first $end
$var wire 1 # out_k_tile_last $end
$var wire 1 ! out_valid $end
$var wire 1 / rst_n $end
$var wire 256 5 out_psum_bus [255:0] $end
$var parameter 32 6 MAX_DELAY $end
$scope begin genblk1[0] $end
$var parameter 32 7 DELAY $end
$var parameter 2 8 c $end
$scope begin genblk1 $end
$upscope $end
$upscope $end
$scope begin genblk1[1] $end
$var parameter 32 9 DELAY $end
$var parameter 2 : c $end
$scope begin genblk1 $end
$upscope $end
$upscope $end
$scope begin genblk1[2] $end
$var parameter 32 ; DELAY $end
$var parameter 3 < c $end
$scope begin genblk1 $end
$upscope $end
$upscope $end
$scope begin genblk1[3] $end
$var parameter 32 = DELAY $end
$var parameter 3 > c $end
$scope begin genblk1 $end
$upscope $end
$upscope $end
$scope begin genblk1[4] $end
$var parameter 32 ? DELAY $end
$var parameter 4 @ c $end
$scope begin genblk1 $end
$upscope $end
$upscope $end
$scope begin genblk1[5] $end
$var parameter 32 A DELAY $end
$var parameter 4 B c $end
$scope begin genblk1 $end
$upscope $end
$upscope $end
$scope begin genblk1[6] $end
$var parameter 32 C DELAY $end
$var parameter 4 D c $end
$scope begin genblk1 $end
$upscope $end
$upscope $end
$scope begin genblk1[7] $end
$var parameter 32 E DELAY $end
$var parameter 4 F c $end
$scope begin genblk1 $end
$upscope $end
$upscope $end
$scope begin $ivl_for_loop0 $end
$var integer 32 G i [31:0] $end
$scope begin $ivl_for_loop1 $end
$var integer 32 H j [31:0] $end
$upscope $end
$upscope $end
$scope begin $ivl_for_loop2 $end
$var integer 32 I i [31:0] $end
$upscope $end
$scope begin $ivl_for_loop3 $end
$var integer 32 J i [31:0] $end
$scope begin $ivl_for_loop4 $end
$var integer 32 K j [31:0] $end
$upscope $end
$upscope $end
$scope begin $ivl_for_loop5 $end
$var integer 32 L k [31:0] $end
$upscope $end
$upscope $end
$scope begin $ivl_for_loop12 $end
$var integer 32 M t [31:0] $end
$scope begin $ivl_for_loop13 $end
$var integer 32 N row [31:0] $end
$scope begin $ivl_for_loop14 $end
$var integer 32 O lane [31:0] $end
$upscope $end
$upscope $end
$upscope $end
$scope begin $ivl_for_loop15 $end
$var integer 32 P t [31:0] $end
$scope begin $ivl_for_loop16 $end
$var integer 32 Q row [31:0] $end
$scope begin $ivl_for_loop17 $end
$var integer 32 R lane [31:0] $end
$upscope $end
$upscope $end
$scope begin $ivl_for_loop18 $end
$var integer 32 S lane [31:0] $end
$upscope $end
$upscope $end
$scope begin $ivl_for_loop6 $end
$var integer 32 T i [31:0] $end
$upscope $end
$scope begin $ivl_for_loop7 $end
$var integer 32 U i [31:0] $end
$upscope $end
$scope begin $ivl_for_loop8 $end
$var integer 32 V t [31:0] $end
$scope begin $ivl_for_loop11 $end
$var integer 32 W lane [31:0] $end
$upscope $end
$scope begin $ivl_for_loop9 $end
$var integer 32 X row [31:0] $end
$scope begin $ivl_for_loop10 $end
$var integer 32 Y lane [31:0] $end
$upscope $end
$upscope $end
$upscope $end
$scope task deskew_pipeline $end
$var reg 32 Z marker_value [31:0] $end
$var integer 32 [ lane_idx [31:0] $end
$upscope $end
$scope task reset_dut $end
$upscope $end
$upscope $end
$enddefinitions $end
$comment Show the parameter values. $end
$dumpall
b111 F
b0 E
b110 D
b1 C
b101 B
b10 A
b100 @
b11 ?
b11 >
b100 =
b10 <
b101 ;
b1 :
b110 9
b0 8
b111 7
b111 6
$end
#0
$dumpvars
b0 [
bx Z
b0 Y
b0 X
b0 W
b0 V
b0 U
b0 T
b0 S
b0 R
b0 Q
b0 P
b0 O
b0 N
b0 M
b0 L
b0 K
b0 J
b111 I
b111 H
b1000 G
b0 5
b0 4
b0 3
b0 2
b0 1
b0 0
0/
x.
bx -
x,
x+
0*
b0 )
0(
0'
0&
0%
0$
0#
b0 "
0!
$end
#5000
b111 I
b111 H
b1000 G
1%
#10000
0%
1/
#15000
1%
#20000
b111 I
b111 H
b1000 G
0/
0%
#25000
b111 I
b111 H
b1000 G
1%
#30000
0%
#35000
b111 I
b111 H
b1000 G
1%
#40000
1/
0%
#45000
1%
#50000
1(
1'
b1 )
b1 4
1&
1*
0%
#55000
b111 L
b1000 J
b111 K
1%
#60000
b111 I
b111 H
b1000 G
0(
0'
b0 )
b0 4
0*
0&
0/
0%
#65000
b111 I
b111 H
b1000 G
1%
#70000
0%
#75000
b111 I
b111 H
b1000 G
1%
#80000
1/
0%
#85000
1%
#90000
0%
#95000
1%
#100000
b111 I
b111 H
b1000 G
0/
0%
#105000
b111 I
b111 H
b1000 G
1%
#110000
0%
#115000
b111 I
b111 H
b1000 G
1%
#120000
1/
0%
#125000
1%
#126000
b1100100 Z
b1100100 3
#130000
1(
1'
1&
1*
b1100100 )
b1100100 4
0%
#135000
b111 L
b111 K
b1000 J
1%
#136000
b11001000 Z
b1 [
b11001000 3
b1 T
#140000
0(
0'
b1100100000000000000000000000000000000000 )
b1100100000000000000000000000000000000000 4
0%
#145000
b111 L
b111 K
b1000 J
1%
#146000
b100101100 Z
b10 [
b100101100 3
b10 T
#150000
b1001011000000000000000000000000000000000000000000000000000000000000000000 )
b1001011000000000000000000000000000000000000000000000000000000000000000000 4
0%
#155000
b111 L
b111 K
b1000 J
1%
#156000
b110010000 Z
b11 [
b110010000 3
b11 T
#160000
b110010000000000000000000000000000000000000000000000000000000000000000000000000000000000000000000000000000 )
b110010000000000000000000000000000000000000000000000000000000000000000000000000000000000000000000000000000 4
0%
#165000
b111 L
b111 K
b1000 J
1%
#166000
b111110100 Z
b100 [
b111110100 3
b100 T
#170000
b11111010000000000000000000000000000000000000000000000000000000000000000000000000000000000000000000000000000000000000000000000000000000000 )
b11111010000000000000000000000000000000000000000000000000000000000000000000000000000000000000000000000000000000000000000000000000000000000 4
0%
#175000
b111 L
b111 K
b1000 J
1%
#176000
b1001011000 Z
b101 [
b1001011000 3
b101 T
#180000
b10010110000000000000000000000000000000000000000000000000000000000000000000000000000000000000000000000000000000000000000000000000000000000000000000000000000000000000000000 )
b10010110000000000000000000000000000000000000000000000000000000000000000000000000000000000000000000000000000000000000000000000000000000000000000000000000000000000000000000 4
0%
#185000
b111 L
b111 K
b1000 J
1%
#186000
b1010111100 Z
b110 [
b1010111100 3
b110 T
#190000
b1010111100000000000000000000000000000000000000000000000000000000000000000000000000000000000000000000000000000000000000000000000000000000000000000000000000000000000000000000000000000000000000000000000000 )
b1010111100000000000000000000000000000000000000000000000000000000000000000000000000000000000000000000000000000000000000000000000000000000000000000000000000000000000000000000000000000000000000000000000000 4
0%
#195000
1#
1$
1!
b1010111100000000000000000000000010010110000000000000000000000000011111010000000000000000000000000110010000000000000000000000000001001011000000000000000000000000001100100000000000000000000000000001100100 "
b1010111100000000000000000000000010010110000000000000000000000000011111010000000000000000000000000110010000000000000000000000000001001011000000000000000000000000001100100000000000000000000000000001100100 5
b111 L
b111 K
b1000 J
1%
#196000
b111 T
#200000
b110010000000000000000000000000001010111100000000000000000000000010010110000000000000000000000000011111010000000000000000000000000110010000000000000000000000000001001011000000000000000000000000001100100000000000000000000000000001100100 "
b110010000000000000000000000000001010111100000000000000000000000010010110000000000000000000000000011111010000000000000000000000000110010000000000000000000000000001001011000000000000000000000000001100100000000000000000000000000001100100 5
b110010000000000000000000000000000000000000000000000000000000000000000000000000000000000000000000000000000000000000000000000000000000000000000000000000000000000000000000000000000000000000000000000000000000000000000000000000000000000000 )
b110010000000000000000000000000000000000000000000000000000000000000000000000000000000000000000000000000000000000000000000000000000000000000000000000000000000000000000000000000000000000000000000000000000000000000000000000000000000000000 4
0%
#205000
0#
0$
b110010000000000000000000000000000000000000000000000000000000000000000000000000000000000000000000000000000000000000000000000000000000000000000000000000000000000000000000000000000000000000000000000000000000000000000000000000000000000000 "
b110010000000000000000000000000000000000000000000000000000000000000000000000000000000000000000000000000000000000000000000000000000000000000000000000000000000000000000000000000000000000000000000000000000000000000000000000000000000000000 5
b111 L
b111 K
b1000 J
1%
#210000
0!
b0 "
b0 5
b111 I
b111 H
b1000 G
b0 )
b0 4
0*
0&
0/
0%
#215000
b111 I
b111 H
b1000 G
1%
#220000
0%
#225000
b111 I
b111 H
b1000 G
1%
#230000
1/
0%
#235000
1%
#236000
b1100100 Z
b0 [
b1100100 3
#240000
1(
1'
1&
1*
b1100100 )
b1100100 4
0%
#245000
b111 L
b111 K
b1000 J
1%
#246000
b11001000 Z
b1 [
b11001000 3
b1 U
#250000
0(
0'
b1100100000000000000000000000000000000000 )
b1100100000000000000000000000000000000000 4
0%
#255000
b111 L
b111 K
b1000 J
1%
#256000
b100101100 Z
b10 [
b100101100 3
b10 U
#260000
b1001011000000000000000000000000000000000000000000000000000000000000000000 )
b1001011000000000000000000000000000000000000000000000000000000000000000000 4
0%
#265000
b111 L
b111 K
b1000 J
1%
#266000
b110010000 Z
b11 [
b110010000 3
b11 U
#270000
b110010000000000000000000000000000000000000000000000000000000000000000000000000000000000000000000000000000 )
b110010000000000000000000000000000000000000000000000000000000000000000000000000000000000000000000000000000 4
0%
#275000
b111 L
b111 K
b1000 J
1%
#276000
b111110100 Z
b100 [
b111110100 3
b100 U
#280000
b11111010000000000000000000000000000000000000000000000000000000000000000000000000000000000000000000000000000000000000000000000000000000000 )
b11111010000000000000000000000000000000000000000000000000000000000000000000000000000000000000000000000000000000000000000000000000000000000 4
0%
#285000
b111 L
b111 K
b1000 J
1%
#286000
b1001011000 Z
b101 [
b1001011000 3
b101 U
#290000
b10010110000000000000000000000000000000000000000000000000000000000000000000000000000000000000000000000000000000000000000000000000000000000000000000000000000000000000000000 )
b10010110000000000000000000000000000000000000000000000000000000000000000000000000000000000000000000000000000000000000000000000000000000000000000000000000000000000000000000 4
0%
#295000
b111 L
b111 K
b1000 J
1%
#296000
b1010111100 Z
b110 [
b1010111100 3
b110 U
#300000
b1010111100000000000000000000000000000000000000000000000000000000000000000000000000000000000000000000000000000000000000000000000000000000000000000000000000000000000000000000000000000000000000000000000000 )
b1010111100000000000000000000000000000000000000000000000000000000000000000000000000000000000000000000000000000000000000000000000000000000000000000000000000000000000000000000000000000000000000000000000000 4
0%
#305000
1#
1$
1!
b1010111100000000000000000000000010010110000000000000000000000000011111010000000000000000000000000110010000000000000000000000000001001011000000000000000000000000001100100000000000000000000000000001100100 "
b1010111100000000000000000000000010010110000000000000000000000000011111010000000000000000000000000110010000000000000000000000000001001011000000000000000000000000001100100000000000000000000000000001100100 5
b111 L
b111 K
b1000 J
1%
#306000
b111 U
b1 0
#310000
b110010000000000000000000000000001010111100000000000000000000000010010110000000000000000000000000011111010000000000000000000000000110010000000000000000000000000001001011000000000000000000000000001100100000000000000000000000000001100100 "
b110010000000000000000000000000001010111100000000000000000000000010010110000000000000000000000000011111010000000000000000000000000110010000000000000000000000000001001011000000000000000000000000001100100000000000000000000000000001100100 5
b110010000000000000000000000000000000000000000000000000000000000000000000000000000000000000000000000000000000000000000000000000000000000000000000000000000000000000000000000000000000000000000000000000000000000000000000000000000000000000 )
b110010000000000000000000000000000000000000000000000000000000000000000000000000000000000000000000000000000000000000000000000000000000000000000000000000000000000000000000000000000000000000000000000000000000000000000000000000000000000000 4
0%
#315000
0#
0$
b110010000000000000000000000000000000000000000000000000000000000000000000000000000000000000000000000000000000000000000000000000000000000000000000000000000000000000000000000000000000000000000000000000000000000000000000000000000000000000 "
b110010000000000000000000000000000000000000000000000000000000000000000000000000000000000000000000000000000000000000000000000000000000000000000000000000000000000000000000000000000000000000000000000000000000000000000000000000000000000000 5
b111 L
b111 K
b1000 J
1%
#320000
0!
b0 "
b0 5
b111 I
b111 H
b1000 G
b0 )
b0 4
0*
0&
0/
0%
#325000
b111 I
b111 H
b1000 G
1%
#330000
0%
#335000
b111 I
b111 H
b1000 G
1%
#340000
1/
0%
#345000
1%
#350000
b1000 X
b1000 Y
b1100101 )
b1100101 4
1(
1'
1*
1&
0%
#351000
b1 V
#355000
b111 L
b111 K
b1000 J
1%
#360000
b1000 Y
b1000 X
b110011000000000000000000000000001101111 )
b110011000000000000000000000000001101111 4
0%
#361000
b10 V
#365000
b111 L
b111 K
b1000 J
1%
#370000
b1000 Y
b1000 X
b11001110000000000000000000000000111000000000000000000000000000001111001 )
b11001110000000000000000000000000111000000000000000000000000000001111001 4
0%
#371000
b11 V
#375000
b111 L
b111 K
b1000 J
1%
#380000
b1000 Y
b1000 X
b1101000000000000000000000000000011100010000000000000000000000000111101000000000000000000000000010000011 )
b1101000000000000000000000000000011100010000000000000000000000000111101000000000000000000000000010000011 4
0%
#381000
b100 V
#385000
b111 L
b111 K
b1000 J
1%
#390000
b1000 Y
b1000 X
b110100100000000000000000000000001110010000000000000000000000000011110110000000000000000000000001000010000000000000000000000000010001101 )
b110100100000000000000000000000001110010000000000000000000000000011110110000000000000000000000001000010000000000000000000000000010001101 4
0%
#391000
b101 V
#395000
b111 L
b111 K
b1000 J
1%
#400000
b1000 Y
b1000 X
b11010100000000000000000000000000111001100000000000000000000000001111100000000000000000000000000100001010000000000000000000000001000111000000000000000000000000010010111 )
b11010100000000000000000000000000111001100000000000000000000000001111100000000000000000000000000100001010000000000000000000000001000111000000000000000000000000010010111 4
0%
#401000
b110 V
#405000
b111 L
b111 K
b1000 J
1%
#410000
b1000 Y
b1000 X
b1101011000000000000000000000000011101000000000000000000000000000111110100000000000000000000000010000110000000000000000000000000100011110000000000000000000000001001100000000000000000000000000010100001 )
b1101011000000000000000000000000011101000000000000000000000000000111110100000000000000000000000010000110000000000000000000000000100011110000000000000000000000001001100000000000000000000000000010100001 4
0%
#411000
b111 V
#415000
1#
1$
1!
b1101011000000000000000000000000011010100000000000000000000000000110100100000000000000000000000001101000000000000000000000000000011001110000000000000000000000000110011000000000000000000000000001100101 "
b1101011000000000000000000000000011010100000000000000000000000000110100100000000000000000000000001101000000000000000000000000000011001110000000000000000000000000110011000000000000000000000000001100101 5
b111 L
b111 K
b1000 J
1%
