rtl/core/pe_mac.sv
`timescale 1ns/1ps

import edgeasic_config_pkg::*;

module pe_mac (

    input  logic clk,
    input  logic rst_n,

    input  logic enable,
    input  logic clear_acc,
    input  logic wgt_load,

    input  logic signed [ACT_W-1:0] act_in,
    input  logic signed [WGT_W-1:0] wgt_in,
    input  logic signed [ACC_W-1:0] psum_in,

    output logic signed [ACT_W-1:0] act_out,
    output logic signed [ACC_W-1:0] psum_out

);

    logic signed [WGT_W-1:0] wgt_reg;
    logic signed [ACT_W+WGT_W-1:0] product;

    always_comb begin
        product = act_in * wgt_reg;
    end

    always_ff @(posedge clk or negedge rst_n) begin
        if (!rst_n) begin
            wgt_reg  <= '0;
            act_out  <= '0;
            psum_out <= '0;
        end else begin

            if (wgt_load) begin
                wgt_reg <= wgt_in;
            end

            if (enable) begin
                act_out <= act_in;

                if (clear_acc) begin
                    psum_out <= product;
                end else begin
                    psum_out <= psum_in + product;
                end
            end

        end
    end

endmodule

tb/tb_pe_mac.sv
`timescale 1ns/1ps



module tb_pe_mac;

    import config_pkg::*;
import types_pkg::*;
    
    logic clk;
    logic rst_n;
    
    logic enable;
    logic clear_acc;
    logic wgt_load;

    logic signed [ACT_W-1:0] act_in;
    logic signed [WGT_W-1:0] wgt_in;
    logic signed [ACC_W-1:0] psum_in;

    logic signed [ACT_W-1:0] act_out;
    logic signed [ACC_W-1:0] psum_out;
    
    int errors;
    pe_mac dut(

        .clk(clk),
        .rst_n(rst_n),
        .enable(enable),
        .clear_acc(clear_acc),
        .wgt_load(wgt_load),
        .act_in(act_in),
        .wgt_in(wgt_in),
        .psum_in(psum_in),
        .act_out(act_out),
        .psum_out(psum_out)

    );

    always #5 clk = ~clk;
    task automatic load_weight;
    input logic signed [WGT_W-1:0] weight_value;
    begin
        @(negedge clk)
        wgt_in = weight_value;
        wgt_load = 1'b1;
        enable = 1'b0;
        clear_acc = 1'b0;

        @(posedge clk)
        #1;

        @(negedge clk)
        wgt_load = 1'b0;
    end
    endtask 

    task automatic run_mac_check;
    input logic signed [ACT_W-1:0] act_value;
    input logic signed [ACC_W-1:0] psum_value;
    input logic clear_value;
    input logic signed [ACC_W-1:0] expected_value;
    input string test_name;
    begin
        @(negedge clk);
        act_in = act_value;
        psum_in = psum_value;
        clear_acc = clear_value;
        enable = 1'b1;
        wgt_load = 1'b0;
        
        @(posedge clk);
        #1;

        if (psum_out !== expected_value) begin
            $display("FAIL : %s expected=%0d got=%0d", test_name, expected_value, psum_out);
            errors++;
        end else begin
            $display("PASS : %s result=%0d", test_name, psum_out);
        end

        if (act_out!== act_value) begin
            $display("FAIL: %s act_out expected=%0d got=%0d", test_name, act_value, act_out);
                errors++;
            end else begin
                $display("PASS: %s act_out registered correctly", test_name);
            end

            @(negedge clk);
            enable    = 1'b0;
            clear_acc = 1'b0;
        end
    endtask
      initial begin
        $dumpfile("sim/pe_mac.vcd");
        $dumpvars(0, tb_pe_mac);

        clk       = 1'b0;
        rst_n     = 1'b0;
        enable    = 1'b0;
        clear_acc = 1'b0;
        wgt_load  = 1'b0;
        act_in    = '0;
        wgt_in    = '0;
        psum_in   = '0;
        errors    = 0;

        #20;
        rst_n = 1'b1;

        #10;

        if (act_out !== '0 || psum_out !== '0) begin
            $display("FAIL: reset outputs not zero");
            errors++;
        end else begin
            $display("PASS: reset outputs zero");
        end

        load_weight(8'sd4);
        run_mac_check(8'sd3, 32'sd0, 1'b1, 32'sd12, "3 * 4");

        load_weight(8'sd4);
        run_mac_check(-8'sd3, 32'sd0, 1'b1, -32'sd12, "-3 * 4");

        load_weight(-8'sd4);
        run_mac_check(-8'sd3, 32'sd0, 1'b1, 32'sd12, "-3 * -4");

        load_weight(8'sd127);
        run_mac_check(8'sd127, 32'sd0, 1'b1, 32'sd16129, "127 * 127");

        load_weight(8'sd127);
        run_mac_check(-8'sd128, 32'sd0, 1'b1, -32'sd16256, "-128 * 127");

        load_weight(8'sd6);
        run_mac_check(8'sd5, 32'sd100, 1'b0, 32'sd130, "100 + 5 * 6");

        load_weight(8'sd7);

        @(negedge clk);
        wgt_in    = 8'sd99;
        act_in    = 8'sd2;
        psum_in   = 32'sd0;
        clear_acc = 1'b1;
        enable    = 1'b1;
        wgt_load  = 1'b0;

        @(posedge clk);
        #1;

        if (psum_out !== 32'sd14) begin
            $display("FAIL: weight-stationary test expected=14 got=%0d", psum_out);
            errors++;
        end else begin
            $display("PASS: weight-stationary test used stored weight, not new wgt_in");
        end

        @(negedge clk);
        enable = 1'b0;

        if (errors == 0) begin
            $display("====================================");
            $display("ALL PE MAC TESTS PASSED");
            $display("====================================");
        end else begin
            $display("====================================");
            $display("PE MAC TESTS FAILED: %0d errors", errors);
            $display("====================================");
        end

        $finish;
    end

endmodule

sim/pe_mac.vcd
$date
	Tue Jul 14 15:06:50 2026
$end
$version
	Icarus Verilog
$end
$timescale
	1ps
$end
$scope module tb_pe_mac $end
$var wire 32 ! psum_out [31:0] $end
$var wire 8 " act_out [7:0] $end
$var reg 8 # act_in [7:0] $end
$var reg 1 $ clear_acc $end
$var reg 1 % clk $end
$var reg 1 & enable $end
$var reg 32 ' psum_in [31:0] $end
$var reg 1 ( rst_n $end
$var reg 8 ) wgt_in [7:0] $end
$var reg 1 * wgt_load $end
$var integer 32 + errors [31:0] $end
$scope module dut $end
$var wire 8 , act_in [7:0] $end
$var wire 1 $ clear_acc $end
$var wire 1 % clk $end
$var wire 1 & enable $end
$var wire 32 - psum_in [31:0] $end
$var wire 1 ( rst_n $end
$var wire 8 . wgt_in [7:0] $end
$var wire 1 * wgt_load $end
$var reg 8 / act_out [7:0] $end
$var reg 16 0 product [15:0] $end
$var reg 32 1 psum_out [31:0] $end
$var reg 8 2 wgt_reg [7:0] $end
$upscope $end
$scope task load_weight $end
$upscope $end
$scope task run_mac_check $end
$upscope $end
$upscope $end
$enddefinitions $end
$comment Show the parameter values. $end
$dumpall
$end
#0
$dumpvars
b0 2
b0 1
b0 0
b0 /
b0 .
b0 -
b0 ,
b0 +
0*
b0 )
0(
b0 '
0&
0%
0$
b0 #
b0 "
b0 !
$end
#5000
1%
#10000
0%
#15000
1%
#20000
0%
1(
#25000
1%
#30000
1*
b100 )
b100 .
0%
#35000
b100 2
1%
#40000
0*
0%
#45000
1%
#50000
b1100 0
1&
1$
b11 #
b11 ,
0%
#55000
b1100 !
b1100 1
b11 "
b11 /
1%
#60000
0$
0&
0%
#65000
1%
#70000
1*
0%
#75000
1%
#80000
0*
0%
#85000
1%
#90000
b1111111111110100 0
1&
1$
b11111101 #
b11111101 ,
0%
#95000
b11111111111111111111111111110100 !
b11111111111111111111111111110100 1
b11111101 "
b11111101 /
1%
#100000
0$
0&
0%
#105000
1%
#110000
1*
b11111100 )
b11111100 .
0%
#115000
b1100 0
b11111100 2
1%
#120000
0*
0%
#125000
1%
#130000
1&
1$
0%
#135000
b1100 !
b1100 1
1%
#140000
0$
0&
0%
#145000
1%
#150000
1*
b1111111 )
b1111111 .
0%
#155000
b1111111010000011 0
b1111111 2
1%
#160000
0*
0%
#165000
1%
#170000
b11111100000001 0
1&
1$
b1111111 #
b1111111 ,
0%
#175000
b11111100000001 !
b11111100000001 1
b1111111 "
b1111111 /
1%
#180000
0$
0&
0%
#185000
1%
#190000
1*
0%
#195000
1%
#200000
0*
0%
#205000
1%
#210000
b1100000010000000 0
1&
1$
b10000000 #
b10000000 ,
0%
#215000
b11111111111111111100000010000000 !
b11111111111111111100000010000000 1
b10000000 "
b10000000 /
1%
#220000
0$
0&
0%
#225000
1%
#230000
1*
b110 )
b110 .
0%
#235000
b1111110100000000 0
b110 2
1%
#240000
0*
0%
#245000
1%
#250000
b11110 0
1&
b1100100 '
b1100100 -
b101 #
b101 ,
0%
#255000
b10000010 !
b10000010 1
b101 "
b101 /
1%
#260000
0&
0%
#265000
1%
#270000
1*
b111 )
b111 .
0%
#275000
b100011 0
b111 2
1%
#280000
0*
0%
#285000
1%
#290000
b1110 0
1&
1$
b0 '
b0 -
b10 #
b10 ,
b1100011 )
b1100011 .
0%
#295000
b1110 !
b1110 1
b10 "
b10 /
1%
#300000
0&
0%
